bracu_cgpa_calc.py
bracu_cgpa_calc-1.0.6.dist-info/LICENSE
bracu_cgpa_calc-1.0.6.dist-info/METADATA
bracu_cgpa_calc-1.0.6.dist-info/WHEEL
bracu_cgpa_calc-1.0.6.dist-info/top_level.txt
bracu_cgpa_calc-1.0.6.dist-info/RECORD
