Metadata-Version: 2.1
Name: bracu-cgpa-calc
Version: 1.0.6
Summary: A CGPA calculator module made for BracU Students.
Home-page: https://github.com/lepotatoguy/bracu-cgpa-module
Author: Joyanta J. Mondal
Author-email: hello@joyantamondal.com
License: UNKNOWN
Keywords: bracu cgpa calculator,cg calculator bracu,bracu cg
Platform: UNKNOWN
Classifier: Programming Language :: Python :: 3
Classifier: License :: OSI Approved :: MIT License
Classifier: Operating System :: OS Independent
Requires-Python: >=3.0
Requires-Dist: XlsxWriter
Requires-Dist: pandas
